{"schemaVersion":{"minor":3,"major":0,"patch":0},"primaryContentSections":[{"kind":"content","content":[{"anchor":"Overview","type":"heading","text":"Overview","level":2},{"type":"paragraph","inlineContent":[{"type":"text","text":"The Composable Architecture is under constant development, and we are always looking for ways to"},{"type":"text","text":" "},{"type":"text","text":"simplify the library, and make it more powerful. As such, we often need to deprecate certain APIs"},{"type":"text","text":" "},{"type":"text","text":"in favor of newer ones. We recommend people update their code as quickly as possible to the newest"},{"type":"text","text":" "},{"type":"text","text":"APIs, and this article contains some tips for doing so."}]},{"items":[{"content":[{"inlineContent":[{"type":"reference","isActive":true,"identifier":"#Using-the-Reducer-macro"}],"type":"paragraph"}]},{"content":[{"type":"paragraph","inlineContent":[{"type":"reference","isActive":true,"identifier":"#Using-case-key-paths"}]}]},{"content":[{"type":"paragraph","inlineContent":[{"isActive":true,"identifier":"#Receiving-test-store-actions","type":"reference"}]}]},{"content":[{"inlineContent":[{"type":"reference","identifier":"#Moving-off-of-TaskResult","isActive":true}],"type":"paragraph"}]},{"content":[{"type":"paragraph","inlineContent":[{"type":"reference","identifier":"#Identified-actions","isActive":true}]}]}],"type":"unorderedList"},{"anchor":"Using-the-Reducer-macro","type":"heading","text":"Using the @Reducer macro","level":3},{"type":"paragraph","inlineContent":[{"text":"Version 1.4 of the library has introduced a new macro for automating certain aspects of implementing","type":"text"},{"text":" ","type":"text"},{"text":"a ","type":"text"},{"type":"reference","identifier":"doc:\/\/ComposableArchitecture\/documentation\/ComposableArchitecture\/Reducer","isActive":true},{"text":". It is called ","type":"text"},{"type":"reference","identifier":"doc:\/\/ComposableArchitecture\/documentation\/ComposableArchitecture\/Reducer()","isActive":true},{"text":", and to migrate existing code one only needs to annotate","type":"text"},{"text":" ","type":"text"},{"text":"their type with ","type":"text"},{"type":"codeVoice","code":"@Reducer"},{"text":":","type":"text"}]},{"syntax":"diff","type":"codeListing","code":["+@Reducer"," struct MyFeature: Reducer {","   \/\/ ..."," }"]},{"type":"paragraph","inlineContent":[{"text":"No other changes to be made, and you can immediately start taking advantage of new capabilities of","type":"text"},{"text":" ","type":"text"},{"text":"reducer composition, such as case key paths (see guides below). See the documentation of","type":"text"},{"text":" ","type":"text"},{"identifier":"doc:\/\/ComposableArchitecture\/documentation\/ComposableArchitecture\/Reducer()","isActive":true,"type":"reference"},{"text":" to see everything that macro adds to your feature’s reducer.","type":"text"}]},{"type":"paragraph","inlineContent":[{"type":"text","text":"You can also technically drop the "},{"type":"reference","identifier":"doc:\/\/ComposableArchitecture\/documentation\/ComposableArchitecture\/Reducer","isActive":true},{"type":"text","text":" conformance:"}]},{"syntax":"diff","type":"codeListing","code":[" @Reducer","-struct MyFeature: Reducer {","+struct MyFeature {","   \/\/ ..."," }"]},{"type":"paragraph","inlineContent":[{"type":"text","text":"However, there are some known issues in Xcode that cause autocomplete and type inference to break."},{"type":"text","text":" "},{"type":"text","text":"See the documentation of "},{"isActive":true,"type":"reference","identifier":"doc:\/\/ComposableArchitecture\/documentation\/ComposableArchitecture\/Reducer#Gotchas"},{"type":"text","text":" for more gotchas on using the "},{"type":"codeVoice","code":"@Reducer"},{"type":"text","text":" macro."}]},{"anchor":"Using-case-key-paths","type":"heading","text":"Using case key paths","level":3},{"type":"paragraph","inlineContent":[{"text":"In version 1.4 we soft-deprecated many APIs that take the ","type":"text"},{"type":"codeVoice","code":"CasePath"},{"text":" type in favor of APIs that take","type":"text"},{"text":" ","type":"text"},{"text":"what is known as a ","type":"text"},{"type":"codeVoice","code":"CaseKeyPath"},{"text":". Both of these types come from our ","type":"text"},{"isActive":true,"type":"reference","identifier":"http:\/\/github.com\/pointfreeco\/swift-case-paths"},{"text":" ","type":"text"},{"text":"library and aim to allow one to abstract over the shape of enums just as key paths allow one to do","type":"text"},{"text":" ","type":"text"},{"text":"so with structs.","type":"text"}]},{"type":"paragraph","inlineContent":[{"text":"However, in conjunction with version 1.4 of this library we also released an update to CasePaths","type":"text"},{"text":" ","type":"text"},{"text":"that massively improved the ergonomics of using case paths. We introduced the ","type":"text"},{"code":"@CasePathable","type":"codeVoice"},{"text":" macro","type":"text"},{"text":" ","type":"text"},{"text":"for automatically deriving case paths so that we could stop using runtime reflection, and we","type":"text"},{"text":" ","type":"text"},{"text":"introduced a way of using key paths to describe case paths. And so the old ","type":"text"},{"code":"CasePath","type":"codeVoice"},{"text":" type has been","type":"text"},{"text":" ","type":"text"},{"text":"deprecated, and the new ","type":"text"},{"code":"CaseKeyPath","type":"codeVoice"},{"text":" type has taken its place.","type":"text"}]},{"type":"paragraph","inlineContent":[{"type":"text","text":"This means that previously when you would use APIs involving case paths you would have to use the"},{"type":"text","text":" "},{"type":"codeVoice","code":"\/"},{"type":"text","text":" prefix operator to derive the case path. For example:"}]},{"code":["Reduce { state, action in ","  \/\/ ...","}",".ifLet(\\.child, action: \/Action.child) {","  ChildFeature()","}"],"syntax":"swift","type":"codeListing"},{"type":"paragraph","inlineContent":[{"text":"You now get to shorten that into a far simpler, more familiar key path syntax:","type":"text"}]},{"code":["Reduce { state, action in ","  \/\/ ...","}",".ifLet(\\.child, action: \\.child) {","  ChildFeature()","}"],"syntax":"swift","type":"codeListing"},{"type":"paragraph","inlineContent":[{"text":"To be able to take advantage of this syntax with your feature’s actions, you must annotate your","type":"text"},{"text":" ","type":"text"},{"identifier":"doc:\/\/ComposableArchitecture\/documentation\/ComposableArchitecture\/Reducer","type":"reference","isActive":true},{"text":" conformances with the ","type":"text"},{"identifier":"doc:\/\/ComposableArchitecture\/documentation\/ComposableArchitecture\/Reducer()","type":"reference","isActive":true},{"text":" macro:","type":"text"}]},{"code":["@Reducer","struct Feature {","  \/\/ ...","}"],"type":"codeListing","syntax":"swift"},{"inlineContent":[{"type":"text","text":"Which automatically applies the "},{"type":"codeVoice","code":"@CasePathable"},{"type":"text","text":" macro to the feature’s "},{"type":"codeVoice","code":"Action"},{"type":"text","text":" enum among other"},{"type":"text","text":" "},{"type":"text","text":"things:"}],"type":"paragraph"},{"code":["+@CasePathable"," enum Action {","   \/\/ ..."," }"],"type":"codeListing","syntax":"diff"},{"type":"paragraph","inlineContent":[{"text":"Further, if the feature’s ","type":"text"},{"code":"State","type":"codeVoice"},{"text":" is an enum, ","type":"text"},{"code":"@CasePathable","type":"codeVoice"},{"text":" will also be applied, along with","type":"text"},{"text":" ","type":"text"},{"code":"@dynamicMemberLookup","type":"codeVoice"},{"text":":","type":"text"}]},{"type":"codeListing","code":["+@CasePathable","+@dynamicMemberLookup"," enum State {","   \/\/ ..."," }"],"syntax":"diff"},{"type":"paragraph","inlineContent":[{"text":"Dynamic member lookups allows a state’s associated value to be accessed via dot-syntax, which can be","type":"text"},{"text":" ","type":"text"},{"text":"useful when scoping a store’s state to a specific case:","type":"text"}]},{"type":"codeListing","code":[" IfLetStore(","   store.scope(","-    state: \/Feature.State.tray, action: Feature.Action.tray","+    state: \\.tray, action: { .tray($0) }","   )",") { store in","  \/\/ ...","}"],"syntax":"diff"},{"type":"paragraph","inlineContent":[{"type":"text","text":"To form a case key path for any other enum, you must apply the "},{"type":"codeVoice","code":"@CasePathable"},{"type":"text","text":" macro explicitly:"}]},{"type":"codeListing","code":["@CasePathable","enum DelegateAction {","  case didFinish(success: Bool)","}"],"syntax":"swift"},{"type":"paragraph","inlineContent":[{"type":"text","text":"And to access its associated values, you must also apply the "},{"type":"codeVoice","code":"@dynamicMemberLookup"},{"type":"text","text":" attributes:"}]},{"type":"codeListing","code":["@CasePathable","@dynamicMemberLookup","enum DestinationState {","  case tray(Tray.State)","}"],"syntax":"swift"},{"type":"paragraph","inlineContent":[{"type":"text","text":"Anywhere you previously used the "},{"code":"\/","type":"codeVoice"},{"type":"text","text":" prefix operator for case paths you should now be able to use"},{"type":"text","text":" "},{"type":"text","text":"key path syntax, so long as all of the enums involved are "},{"code":"@CasePathable","type":"codeVoice"},{"type":"text","text":"."}]},{"type":"paragraph","inlineContent":[{"type":"text","text":"If you encounter any problems, create a "},{"type":"reference","identifier":"http:\/\/github.com\/pointfreeco\/swift-composable-architecture\/discussions","isActive":true},{"type":"text","text":" on the Composable Architecture"},{"type":"text","text":" "},{"type":"text","text":"repo."}]},{"type":"heading","level":3,"anchor":"Receiving-test-store-actions","text":"Receiving test store actions"},{"type":"paragraph","inlineContent":[{"text":"The power of case key paths and the ","type":"text"},{"code":"@CasePathable","type":"codeVoice"},{"text":" macro has made it possible to massively simplify","type":"text"},{"text":" ","type":"text"},{"text":"how one asserts on actions received in a ","type":"text"},{"type":"reference","identifier":"doc:\/\/ComposableArchitecture\/documentation\/ComposableArchitecture\/TestStore","isActive":true},{"text":". Instead of constructing the concrete action","type":"text"},{"text":" ","type":"text"},{"text":"received from an effect like this:","type":"text"}]},{"type":"codeListing","code":["store.receive(.child(.presented(.response(.success(\"Hello!\")))))"],"syntax":"swift"},{"type":"paragraph","inlineContent":[{"text":"…you can use key path syntax to describe the nesting of action cases that is received:","type":"text"}]},{"type":"codeListing","code":["store.receive(\\.child.presented.response.success)"],"syntax":"swift"},{"type":"aside","content":[{"type":"paragraph","inlineContent":[{"type":"text","text":"Case key path syntax requires that every nested action is "},{"type":"codeVoice","code":"@CasePathable"},{"type":"text","text":". Reducer actions"},{"type":"text","text":" "},{"type":"text","text":"are typically "},{"type":"codeVoice","code":"@CasePathable"},{"type":"text","text":" automatically via the "},{"type":"reference","identifier":"doc:\/\/ComposableArchitecture\/documentation\/ComposableArchitecture\/Reducer()","isActive":true},{"type":"text","text":" macro, but other enums must be"},{"type":"text","text":" "},{"type":"text","text":"explicitly annotated:"}]},{"type":"codeListing","syntax":"swift","code":["@CasePathable","enum DelegateAction {","  case didFinish(success: Bool)","}"]}],"style":"note","name":"Note"},{"type":"paragraph","inlineContent":[{"text":"And in the case of ","type":"text"},{"isActive":true,"identifier":"doc:\/\/ComposableArchitecture\/documentation\/ComposableArchitecture\/PresentationAction","type":"reference"},{"text":" you can even omit the ","type":"text"},{"isActive":true,"identifier":"doc:\/\/ComposableArchitecture\/documentation\/ComposableArchitecture\/PresentationAction\/presented(_:)","type":"reference"},{"text":" ","type":"text"},{"text":"path component:","type":"text"}]},{"type":"codeListing","code":["store.receive(\\.child.response.success)"],"syntax":"swift"},{"type":"paragraph","inlineContent":[{"type":"text","text":"This does not assert on the "},{"type":"emphasis","inlineContent":[{"type":"text","text":"data"}]},{"type":"text","text":" received in the action, but typically that is already covered"},{"type":"text","text":" "},{"type":"text","text":"by the state assertion made inside the trailing closure of "},{"type":"codeVoice","code":"receive"},{"type":"text","text":". And if you use this style of"},{"type":"text","text":" "},{"type":"text","text":"action receiving exclusively, you can even stop conforming your action types to "},{"type":"codeVoice","code":"Equatable"},{"type":"text","text":"."}]},{"type":"paragraph","inlineContent":[{"type":"text","text":"There are a few advanced situations to be aware of. When receiving an action that involves an"},{"type":"text","text":" "},{"type":"reference","isActive":true,"identifier":"doc:\/\/ComposableArchitecture\/documentation\/ComposableArchitecture\/IdentifiedAction"},{"type":"text","text":" (more information below in "},{"type":"reference","isActive":true,"identifier":"doc:\/\/ComposableArchitecture\/documentation\/ComposableArchitecture\/MigratingTo1.4#Identified-actions"},{"type":"text","text":"), then"},{"type":"text","text":" "},{"type":"text","text":"you can use the subscript "},{"type":"reference","isActive":true,"identifier":"doc:\/\/ComposableArchitecture\/documentation\/ComposableArchitecture\/IdentifiedAction\/AllCasePaths-swift.struct\/subscript(id:)"},{"type":"text","text":" to"},{"type":"text","text":" "},{"type":"text","text":"receive a particular action for an element:"}]},{"type":"codeListing","code":["store.receive(\\.rows[id: 0].response.success)"],"syntax":"swift"},{"type":"paragraph","inlineContent":[{"text":"And the same goes for ","type":"text"},{"identifier":"doc:\/\/ComposableArchitecture\/documentation\/ComposableArchitecture\/StackAction","isActive":true,"type":"reference"},{"text":" too:","type":"text"}]},{"type":"codeListing","code":["store.receive(\\.path[id: 0].response.success)"],"syntax":"swift"},{"type":"heading","level":3,"anchor":"Moving-off-of-TaskResult","text":"Moving off of TaskResult"},{"type":"paragraph","inlineContent":[{"type":"text","text":"In version 1.4 of the library, the "},{"type":"reference","isActive":true,"identifier":"doc:\/\/ComposableArchitecture\/documentation\/ComposableArchitecture\/TaskResult"},{"type":"text","text":" was soft-deprecated and eventually will be fully"},{"type":"text","text":" "},{"type":"text","text":"deprecated and then removed. The original rationale for the introduction of "},{"type":"reference","isActive":true,"identifier":"doc:\/\/ComposableArchitecture\/documentation\/ComposableArchitecture\/TaskResult"},{"type":"text","text":" was to"},{"type":"text","text":" "},{"type":"text","text":"make an equatable-friendly version of "},{"code":"Result","type":"codeVoice"},{"type":"text","text":" for when the error produced was "},{"code":"any Error","type":"codeVoice"},{"type":"text","text":", which is"},{"type":"text","text":" "},{"type":"text","text":"not equatable. And the reason to want an equatable-friendly result is so that the "},{"code":"Action","type":"codeVoice"},{"type":"text","text":" type in"},{"type":"text","text":" "},{"type":"text","text":"reducers can be equatable, and the reason for "},{"type":"emphasis","inlineContent":[{"text":"that","type":"text"}]},{"type":"text","text":" is to make it possible to test actions"},{"type":"text","text":" "},{"type":"text","text":"emitted by effects."}]},{"type":"paragraph","inlineContent":[{"type":"text","text":"Typically in tests, when one wants to assert that the "},{"type":"reference","isActive":true,"identifier":"doc:\/\/ComposableArchitecture\/documentation\/ComposableArchitecture\/TestStore"},{"type":"text","text":" received an action you must"},{"type":"text","text":" "},{"type":"text","text":"specify a concrete action:"}]},{"type":"codeListing","code":["store.receive(.response(.success(\"Hello!\"))) {","  \/\/ ...","}"],"syntax":"swift"},{"type":"paragraph","inlineContent":[{"text":"The ","type":"text"},{"identifier":"doc:\/\/ComposableArchitecture\/documentation\/ComposableArchitecture\/TestStore","type":"reference","isActive":true},{"text":" uses the equatable conformance of ","type":"text"},{"code":"Action","type":"codeVoice"},{"text":" to confirm that you are asserting that","type":"text"},{"text":" ","type":"text"},{"text":"the store received the correct action.","type":"text"}]},{"type":"paragraph","inlineContent":[{"text":"However, this becomes verbose when testing deeply nested features, which is common in integration","type":"text"},{"text":" ","type":"text"},{"text":"tests:","type":"text"}]},{"type":"codeListing","code":["store.receive(.child(.response(.success(\"Hello!\")))) {","  \/\/ ...","}"],"syntax":"swift"},{"type":"paragraph","inlineContent":[{"text":"However, with the introduction of ","type":"text"},{"overridingTitleInlineContent":[{"type":"text","text":"case key paths"}],"isActive":true,"type":"reference","identifier":"http:\/\/github.com\/pointfreeco\/swift-case-paths","overridingTitle":"case key paths"},{"text":" we greatly improved the","type":"text"},{"text":" ","type":"text"},{"text":"ergonomics of referring to deeply nested enums. You can now use key path syntax to describe the","type":"text"},{"text":" ","type":"text"},{"text":"case of the enum you expect to receive, and you can even omit the associated data from the action","type":"text"},{"text":" ","type":"text"},{"text":"since typically that is covered in the state assertion:","type":"text"}]},{"type":"codeListing","code":["store.receive(\\.child.response.success) {","  \/\/ ...","}"],"syntax":"swift"},{"type":"paragraph","inlineContent":[{"text":"And this syntax does not require the ","type":"text"},{"type":"codeVoice","code":"Action"},{"text":" enum to be equatable since we are only asserting that","type":"text"},{"text":" ","type":"text"},{"text":"the case of the action was received. We are not testing the data in the action.","type":"text"}]},{"type":"paragraph","inlineContent":[{"type":"text","text":"We feel that with this better syntax there is less of a reason to have "},{"isActive":true,"identifier":"doc:\/\/ComposableArchitecture\/documentation\/ComposableArchitecture\/TaskResult","type":"reference"},{"type":"text","text":" and so we"},{"type":"text","text":" "},{"type":"text","text":"do plan on removing it eventually. If you have an important use case for "},{"isActive":true,"identifier":"doc:\/\/ComposableArchitecture\/documentation\/ComposableArchitecture\/TaskResult","type":"reference"},{"type":"text","text":" that you"},{"type":"text","text":" "},{"type":"text","text":"think merits it being in the library, please "},{"isActive":true,"overridingTitle":"open a discussion","identifier":"http:\/\/github.com\/pointfreeco\/swift-composable-architecture\/discussions","overridingTitleInlineContent":[{"type":"text","text":"open a discussion"}],"type":"reference"},{"type":"text","text":"."}]},{"type":"heading","level":3,"anchor":"Identified-actions","text":"Identified actions"},{"type":"paragraph","inlineContent":[{"text":"In version 1.4 of the library we introduced the ","type":"text"},{"type":"reference","isActive":true,"identifier":"doc:\/\/ComposableArchitecture\/documentation\/ComposableArchitecture\/IdentifiedAction"},{"text":" type which makes it more","type":"text"},{"text":" ","type":"text"},{"text":"ergonomic to bundle the data needed for actions in collections of data. Previously you would","type":"text"},{"text":" ","type":"text"},{"text":"have a case in your ","type":"text"},{"type":"codeVoice","code":"Action"},{"text":" enum for a particular row that holds the ID of the state being acted","type":"text"},{"text":" ","type":"text"},{"text":"upon as well as the action:","type":"text"}]},{"type":"codeListing","code":["enum Action {","  \/\/ ...","  case row(id: State.ID, action: Action)","}"],"syntax":"swift"},{"type":"paragraph","inlineContent":[{"text":"This can be updated to hold onto ","type":"text"},{"identifier":"doc:\/\/ComposableArchitecture\/documentation\/ComposableArchitecture\/IdentifiedAction","type":"reference","isActive":true},{"text":" instead of those piece of data directly in the","type":"text"},{"text":" ","type":"text"},{"text":"case:","type":"text"}]},{"type":"codeListing","code":["enum Action {","  \/\/ ...","  case rows(IdentifiedActionOf<Nested>)","}"],"syntax":"swift"},{"type":"paragraph","inlineContent":[{"type":"text","text":"And in the reducer, instead of invoking"},{"type":"text","text":" "},{"type":"reference","isActive":true,"identifier":"doc:\/\/ComposableArchitecture\/documentation\/ComposableArchitecture\/Reducer\/forEach(_:action:element:fileID:filePath:line:column:)-6zye8"},{"type":"text","text":" with a case path using the"},{"type":"text","text":" "},{"type":"codeVoice","code":"\/"},{"type":"text","text":" prefix operator:"}]},{"type":"codeListing","code":["Reduce { state, action in ","  \/\/ ...","}",".forEach(\\.rows, action: \/Action.row(id:action:)) {","  RowFeature()","}"],"syntax":"swift"},{"type":"paragraph","inlineContent":[{"type":"text","text":"…you will instead use key path syntax to determine which case of the "},{"type":"codeVoice","code":"Action"},{"type":"text","text":" enum holds the"},{"type":"text","text":" "},{"type":"text","text":"identified action:"}]},{"type":"codeListing","code":["Reduce { state, action in ","  \/\/ ...","}",".forEach(\\.rows, action: \\.rows) {","  RowFeature()","}"],"syntax":"swift"},{"type":"paragraph","inlineContent":[{"type":"text","text":"This syntax is shorter, more familiar, and can better leverage Xcode autocomplete and"},{"type":"text","text":" "},{"type":"text","text":"type-inference."}]},{"type":"paragraph","inlineContent":[{"type":"text","text":"One last change you will need to make is anywhere you are destructuring the old-style action you"},{"type":"text","text":" "},{"type":"text","text":"will need to insert a "},{"code":".element","type":"codeVoice"},{"type":"text","text":" layer:"}]},{"type":"codeListing","code":["-case let .row(id: id, action: .buttonTapped):","+case let .rows(.element(id: id, action: .buttonTapped)):"],"syntax":"diff"}]}],"seeAlsoSections":[{"identifiers":["doc:\/\/ComposableArchitecture\/documentation\/ComposableArchitecture\/MigratingTo1.19","doc:\/\/ComposableArchitecture\/documentation\/ComposableArchitecture\/MigratingTo1.18","doc:\/\/ComposableArchitecture\/documentation\/ComposableArchitecture\/MigratingTo1.17.1","doc:\/\/ComposableArchitecture\/documentation\/ComposableArchitecture\/MigratingTo1.17","doc:\/\/ComposableArchitecture\/documentation\/ComposableArchitecture\/MigratingTo1.16","doc:\/\/ComposableArchitecture\/documentation\/ComposableArchitecture\/MigratingTo1.15","doc:\/\/ComposableArchitecture\/documentation\/ComposableArchitecture\/MigratingTo1.14","doc:\/\/ComposableArchitecture\/documentation\/ComposableArchitecture\/MigratingTo1.13","doc:\/\/ComposableArchitecture\/documentation\/ComposableArchitecture\/MigratingTo1.12","doc:\/\/ComposableArchitecture\/documentation\/ComposableArchitecture\/MigratingTo1.11","doc:\/\/ComposableArchitecture\/documentation\/ComposableArchitecture\/MigratingTo1.10","doc:\/\/ComposableArchitecture\/documentation\/ComposableArchitecture\/MigratingTo1.9","doc:\/\/ComposableArchitecture\/documentation\/ComposableArchitecture\/MigratingTo1.8","doc:\/\/ComposableArchitecture\/documentation\/ComposableArchitecture\/MigratingTo1.7","doc:\/\/ComposableArchitecture\/documentation\/ComposableArchitecture\/MigratingTo1.6","doc:\/\/ComposableArchitecture\/documentation\/ComposableArchitecture\/MigratingTo1.5"],"generated":true}],"identifier":{"url":"doc:\/\/ComposableArchitecture\/documentation\/ComposableArchitecture\/MigratingTo1.4","interfaceLanguage":"swift"},"metadata":{"title":"Migrating to 1.4","modules":[{"name":"ComposableArchitecture"}],"roleHeading":"Article","role":"article"},"abstract":[{"type":"text","text":"Update your code to make use of the "},{"type":"reference","isActive":true,"identifier":"doc:\/\/ComposableArchitecture\/documentation\/ComposableArchitecture\/Reducer()"},{"type":"text","text":" macro, and learn how to better leverage case key"},{"type":"text","text":" "},{"type":"text","text":"paths in your features."}],"kind":"article","hierarchy":{"paths":[["doc:\/\/ComposableArchitecture\/documentation\/ComposableArchitecture","doc:\/\/ComposableArchitecture\/documentation\/ComposableArchitecture\/MigrationGuides"]]},"variants":[{"paths":["\/documentation\/composablearchitecture\/migratingto1.4"],"traits":[{"interfaceLanguage":"swift"}]}],"sections":[],"references":{"doc://ComposableArchitecture/documentation/ComposableArchitecture/WithViewStore":{"identifier":"doc:\/\/ComposableArchitecture\/documentation\/ComposableArchitecture\/WithViewStore","role":"symbol","abstract":[{"text":"A view helper that transforms a ","type":"text"},{"isActive":true,"type":"reference","identifier":"doc:\/\/ComposableArchitecture\/documentation\/ComposableArchitecture\/Store"},{"text":" into a ","type":"text"},{"isActive":true,"type":"reference","identifier":"doc:\/\/ComposableArchitecture\/documentation\/ComposableArchitecture\/ViewStore"},{"text":" so that its state can be observed","type":"text"},{"text":" ","type":"text"},{"text":"by a view builder.","type":"text"}],"title":"WithViewStore","type":"topic","fragments":[{"kind":"keyword","text":"struct"},{"kind":"text","text":" "},{"kind":"identifier","text":"WithViewStore"}],"deprecated":true,"kind":"symbol","url":"\/documentation\/composablearchitecture\/withviewstore","navigatorTitle":[{"kind":"identifier","text":"WithViewStore"}]},"doc://ComposableArchitecture/documentation/ComposableArchitecture/MigratingTo1.7":{"type":"topic","kind":"article","identifier":"doc:\/\/ComposableArchitecture\/documentation\/ComposableArchitecture\/MigratingTo1.7","abstract":[{"type":"text","text":"Update your code to make use of the new observation tools in the library and get rid of legacy"},{"type":"text","text":" "},{"type":"text","text":"APIs such as "},{"type":"reference","identifier":"doc:\/\/ComposableArchitecture\/documentation\/ComposableArchitecture\/WithViewStore","isActive":true},{"type":"text","text":", "},{"type":"reference","identifier":"doc:\/\/ComposableArchitecture\/documentation\/ComposableArchitecture\/IfLetStore","isActive":true},{"type":"text","text":", "},{"type":"reference","identifier":"doc:\/\/ComposableArchitecture\/documentation\/ComposableArchitecture\/ForEachStore","isActive":true},{"type":"text","text":", and more."}],"url":"\/documentation\/composablearchitecture\/migratingto1.7","role":"article","title":"Migrating to 1.7"},"http://github.com/pointfreeco/swift-case-paths":{"type":"link","titleInlineContent":[{"type":"text","text":"CasePaths"}],"identifier":"http:\/\/github.com\/pointfreeco\/swift-case-paths","url":"http:\/\/github.com\/pointfreeco\/swift-case-paths","title":"CasePaths"},"doc://ComposableArchitecture/documentation/ComposableArchitecture/Reducer#Gotchas":{"type":"topic","kind":"section","abstract":[],"identifier":"doc:\/\/ComposableArchitecture\/documentation\/ComposableArchitecture\/Reducer#Gotchas","url":"\/documentation\/composablearchitecture\/reducer#Gotchas","title":"Gotchas"},"doc://ComposableArchitecture/documentation/ComposableArchitecture/MigratingTo1.13":{"type":"topic","role":"article","abstract":[{"text":"The Composable Architecture now provides first class tools for building features in UIKit,","type":"text"},{"text":" ","type":"text"},{"text":"including minimal state observation, presentation and stack navigation.","type":"text"}],"url":"\/documentation\/composablearchitecture\/migratingto1.13","identifier":"doc:\/\/ComposableArchitecture\/documentation\/ComposableArchitecture\/MigratingTo1.13","title":"Migrating to 1.13","kind":"article"},"doc://ComposableArchitecture/documentation/ComposableArchitecture/MigratingTo1.10":{"title":"Migrating to 1.10","kind":"article","identifier":"doc:\/\/ComposableArchitecture\/documentation\/ComposableArchitecture\/MigratingTo1.10","role":"article","abstract":[{"text":"Update your code to make use of the new state sharing tools in the library, such as the ","type":"text"},{"code":"Shared","type":"codeVoice"},{"text":" ","type":"text"},{"text":"property wrapper, and the ","type":"text"},{"code":"appStorage","type":"codeVoice"},{"text":" and ","type":"text"},{"code":"fileStorage","type":"codeVoice"},{"text":" persistence strategies.","type":"text"}],"type":"topic","url":"\/documentation\/composablearchitecture\/migratingto1.10"},"doc://ComposableArchitecture/documentation/ComposableArchitecture/TaskResult":{"fragments":[{"text":"enum","kind":"keyword"},{"text":" ","kind":"text"},{"text":"TaskResult","kind":"identifier"}],"identifier":"doc:\/\/ComposableArchitecture\/documentation\/ComposableArchitecture\/TaskResult","role":"symbol","abstract":[{"text":"A value that represents either a success or a failure. This type differs from Swift’s ","type":"text"},{"code":"Result","type":"codeVoice"},{"text":" ","type":"text"},{"text":"type in that it uses only one generic for the success case, leaving the failure case as an","type":"text"},{"text":" ","type":"text"},{"text":"untyped ","type":"text"},{"code":"Error","type":"codeVoice"},{"text":".","type":"text"}],"navigatorTitle":[{"text":"TaskResult","kind":"identifier"}],"type":"topic","url":"\/documentation\/composablearchitecture\/taskresult","deprecated":true,"title":"TaskResult","kind":"symbol"},"doc://ComposableArchitecture/documentation/ComposableArchitecture/MigratingTo1.12":{"identifier":"doc:\/\/ComposableArchitecture\/documentation\/ComposableArchitecture\/MigratingTo1.12","abstract":[{"text":"Take advantage of custom decoding and encoding logic for the shared file storage persistence","type":"text"},{"text":" ","type":"text"},{"text":"strategy, as well as beta support for Swift’s native Testing framework.","type":"text"}],"url":"\/documentation\/composablearchitecture\/migratingto1.12","kind":"article","role":"article","type":"topic","title":"Migrating to 1.12"},"doc://ComposableArchitecture/documentation/ComposableArchitecture/MigratingTo1.17":{"role":"article","title":"Migrating to 1.17","kind":"article","type":"topic","identifier":"doc:\/\/ComposableArchitecture\/documentation\/ComposableArchitecture\/MigratingTo1.17","url":"\/documentation\/composablearchitecture\/migratingto1.17","abstract":[{"text":"The ","type":"text"},{"code":"@Shared","type":"codeVoice"},{"text":" property wrapper and related tools have been extracted to their own","type":"text"},{"text":" ","type":"text"},{"text":"library so that they can be used in non-Composable Architecture applications. This a","type":"text"},{"text":" ","type":"text"},{"text":"backwards compatible change, but some new deprecations have been introduced.","type":"text"}]},"#Moving-off-of-TaskResult":{"type":"link","titleInlineContent":[{"type":"text","text":"Moving off of "},{"type":"codeVoice","code":"TaskResult"}],"identifier":"#Moving-off-of-TaskResult","url":"#Moving-off-of-TaskResult","title":"Moving off of TaskResult"},"doc://ComposableArchitecture/documentation/ComposableArchitecture/MigratingTo1.15":{"type":"topic","kind":"article","identifier":"doc:\/\/ComposableArchitecture\/documentation\/ComposableArchitecture\/MigratingTo1.15","abstract":[{"type":"text","text":"The library has been completely updated for Swift 6 language mode, and now compiles in strict"},{"type":"text","text":" "},{"type":"text","text":"concurrency with no warnings or errors."}],"url":"\/documentation\/composablearchitecture\/migratingto1.15","role":"article","title":"Migrating to 1.15"},"doc://ComposableArchitecture/documentation/ComposableArchitecture/MigratingTo1.8":{"kind":"article","abstract":[{"text":"Update your code to make use of the new capabilities of the ","type":"text"},{"isActive":true,"identifier":"doc:\/\/ComposableArchitecture\/documentation\/ComposableArchitecture\/Reducer()","type":"reference"},{"text":" macro, including automatic","type":"text"},{"text":" ","type":"text"},{"text":"fulfillment of requirements for destination reducers and path reducers.","type":"text"}],"title":"Migrating to 1.8","role":"article","url":"\/documentation\/composablearchitecture\/migratingto1.8","identifier":"doc:\/\/ComposableArchitecture\/documentation\/ComposableArchitecture\/MigratingTo1.8","type":"topic"},"doc://ComposableArchitecture/documentation/ComposableArchitecture/PresentationAction":{"navigatorTitle":[{"kind":"identifier","text":"PresentationAction"}],"title":"PresentationAction","abstract":[{"text":"A wrapper type for actions that can be presented.","type":"text"}],"kind":"symbol","fragments":[{"kind":"keyword","text":"enum"},{"kind":"text","text":" "},{"kind":"identifier","text":"PresentationAction"}],"role":"symbol","identifier":"doc:\/\/ComposableArchitecture\/documentation\/ComposableArchitecture\/PresentationAction","url":"\/documentation\/composablearchitecture\/presentationaction","type":"topic"},"doc://ComposableArchitecture/documentation/ComposableArchitecture/IfLetStore":{"identifier":"doc:\/\/ComposableArchitecture\/documentation\/ComposableArchitecture\/IfLetStore","role":"symbol","deprecated":true,"type":"topic","fragments":[{"kind":"keyword","text":"struct"},{"kind":"text","text":" "},{"kind":"identifier","text":"IfLetStore"}],"title":"IfLetStore","abstract":[{"type":"text","text":"A view that safely unwraps a store of optional state in order to show one of two views."}],"url":"\/documentation\/composablearchitecture\/ifletstore","kind":"symbol","navigatorTitle":[{"kind":"identifier","text":"IfLetStore"}]},"#Receiving-test-store-actions":{"type":"link","titleInlineContent":[{"type":"text","text":"Receiving test store actions"}],"identifier":"#Receiving-test-store-actions","url":"#Receiving-test-store-actions","title":"Receiving test store actions"},"doc://ComposableArchitecture/documentation/ComposableArchitecture/Store/scope(state:action:)-90255":{"abstract":[{"type":"text","text":"Scopes the store to one that exposes child state and actions."}],"url":"\/documentation\/composablearchitecture\/store\/scope(state:action:)-90255","type":"topic","fragments":[{"kind":"keyword","text":"func"},{"kind":"text","text":" "},{"kind":"identifier","text":"scope"},{"kind":"text","text":"<"},{"kind":"genericParameter","text":"ChildState"},{"kind":"text","text":", "},{"kind":"genericParameter","text":"ChildAction"},{"kind":"text","text":">("},{"kind":"externalParam","text":"state"},{"kind":"text","text":": "},{"kind":"typeIdentifier","text":"KeyPath","preciseIdentifier":"s:s7KeyPathC"},{"kind":"text","text":"<"},{"kind":"typeIdentifier","text":"State"},{"kind":"text","text":", "},{"kind":"typeIdentifier","text":"ChildState"},{"kind":"text","text":">, "},{"kind":"externalParam","text":"action"},{"kind":"text","text":": "},{"kind":"typeIdentifier","text":"CaseKeyPath","preciseIdentifier":"s:9CasePaths0A7KeyPatha"},{"kind":"text","text":"<"},{"kind":"typeIdentifier","text":"Action"},{"kind":"text","text":", "},{"kind":"typeIdentifier","text":"ChildAction"},{"kind":"text","text":">) -> "},{"kind":"typeIdentifier","text":"Store","preciseIdentifier":"s:22ComposableArchitecture5StoreC"},{"kind":"text","text":"<"},{"kind":"typeIdentifier","text":"ChildState"},{"kind":"text","text":", "},{"kind":"typeIdentifier","text":"ChildAction"},{"kind":"text","text":">"}],"role":"symbol","kind":"symbol","title":"scope(state:action:)","identifier":"doc:\/\/ComposableArchitecture\/documentation\/ComposableArchitecture\/Store\/scope(state:action:)-90255"},"doc://ComposableArchitecture/documentation/ComposableArchitecture/IdentifiedAction/AllCasePaths-swift.struct/subscript(id:)":{"title":"subscript(id:)","url":"\/documentation\/composablearchitecture\/identifiedaction\/allcasepaths-swift.struct\/subscript(id:)","kind":"symbol","type":"topic","abstract":[],"role":"symbol","identifier":"doc:\/\/ComposableArchitecture\/documentation\/ComposableArchitecture\/IdentifiedAction\/AllCasePaths-swift.struct\/subscript(id:)","fragments":[{"kind":"keyword","text":"subscript"},{"kind":"text","text":"("},{"kind":"externalParam","text":"id"},{"kind":"text","text":" _: "},{"kind":"typeIdentifier","text":"ID"},{"kind":"text","text":") -> "},{"kind":"typeIdentifier","text":"AnyCasePath","preciseIdentifier":"s:9CasePaths03AnyA4PathV"},{"kind":"text","text":"<"},{"kind":"typeIdentifier","text":"IdentifiedAction","preciseIdentifier":"s:22ComposableArchitecture16IdentifiedActionO"},{"kind":"text","text":"<"},{"kind":"typeIdentifier","text":"ID"},{"kind":"text","text":", "},{"kind":"typeIdentifier","text":"Action"},{"kind":"text","text":">, "},{"kind":"typeIdentifier","text":"Action"},{"kind":"text","text":">"}]},"doc://ComposableArchitecture/documentation/ComposableArchitecture/MigratingTo1.19":{"url":"\/documentation\/composablearchitecture\/migratingto1.19","abstract":[{"text":"Store internals have been rewritten for performance and future features, and are now compatible with","type":"text"},{"text":" ","type":"text"},{"text":"SwiftUI’s ","type":"text"},{"code":"@StateObject","type":"codeVoice"},{"text":" property wrapper.","type":"text"}],"type":"topic","identifier":"doc:\/\/ComposableArchitecture\/documentation\/ComposableArchitecture\/MigratingTo1.19","kind":"article","title":"Migrating to 1.19","role":"article"},"doc://ComposableArchitecture/documentation/ComposableArchitecture/MigratingTo1.16":{"abstract":[{"type":"text","text":"The "},{"type":"codeVoice","code":".appStorage"},{"type":"text","text":" strategy used with "},{"type":"codeVoice","code":"@Shared"},{"type":"text","text":" now uses key-value observing instead of"},{"type":"text","text":" "},{"type":"codeVoice","code":"NotificationCenter"},{"type":"text","text":" when possible. Learn how this may affect your code."}],"type":"topic","identifier":"doc:\/\/ComposableArchitecture\/documentation\/ComposableArchitecture\/MigratingTo1.16","title":"Migrating to 1.16","kind":"article","url":"\/documentation\/composablearchitecture\/migratingto1.16","role":"article"},"doc://ComposableArchitecture/documentation/ComposableArchitecture/IdentifiedAction":{"abstract":[{"text":"A wrapper type for actions that can be presented in a list.","type":"text"}],"navigatorTitle":[{"text":"IdentifiedAction","kind":"identifier"}],"type":"topic","identifier":"doc:\/\/ComposableArchitecture\/documentation\/ComposableArchitecture\/IdentifiedAction","fragments":[{"text":"enum","kind":"keyword"},{"text":" ","kind":"text"},{"text":"IdentifiedAction","kind":"identifier"}],"title":"IdentifiedAction","kind":"symbol","role":"symbol","url":"\/documentation\/composablearchitecture\/identifiedaction"},"doc://ComposableArchitecture/documentation/ComposableArchitecture/MigratingTo1.6":{"abstract":[{"text":"Update your code to make use of the new","type":"text"},{"text":" ","type":"text"},{"code":"TestStore\/receive(_:_:timeout:assert:fileID:file:line:column:)-9jd7x","type":"codeVoice"},{"text":" method when you need to","type":"text"},{"text":" ","type":"text"},{"text":"assert on the payload inside an action received.","type":"text"}],"title":"Migrating to 1.6","url":"\/documentation\/composablearchitecture\/migratingto1.6","role":"article","kind":"article","identifier":"doc:\/\/ComposableArchitecture\/documentation\/ComposableArchitecture\/MigratingTo1.6","type":"topic"},"doc://ComposableArchitecture/documentation/ComposableArchitecture/MigratingTo1.18":{"kind":"article","identifier":"doc:\/\/ComposableArchitecture\/documentation\/ComposableArchitecture\/MigratingTo1.18","role":"article","title":"Migrating to 1.18","url":"\/documentation\/composablearchitecture\/migratingto1.18","abstract":[{"text":"Stores now automatically cancel their in-flight effects when they deallocate. And another UIKit","type":"text"},{"text":" ","type":"text"},{"text":"navigation helper has been introduced.","type":"text"}],"type":"topic"},"doc://ComposableArchitecture/documentation/ComposableArchitecture/StackAction":{"title":"StackAction","abstract":[{"text":"A wrapper type for actions that can be presented in a navigation stack.","type":"text"}],"role":"symbol","kind":"symbol","type":"topic","url":"\/documentation\/composablearchitecture\/stackaction","fragments":[{"kind":"keyword","text":"enum"},{"kind":"text","text":" "},{"kind":"identifier","text":"StackAction"}],"navigatorTitle":[{"kind":"identifier","text":"StackAction"}],"identifier":"doc:\/\/ComposableArchitecture\/documentation\/ComposableArchitecture\/StackAction"},"doc://ComposableArchitecture/documentation/ComposableArchitecture/MigrationGuides":{"type":"topic","role":"collectionGroup","abstract":[{"text":"Learn how to upgrade your application to the newest version of the Composable Architecture.","type":"text"}],"url":"\/documentation\/composablearchitecture\/migrationguides","identifier":"doc:\/\/ComposableArchitecture\/documentation\/ComposableArchitecture\/MigrationGuides","title":"Migration guides","kind":"article"},"doc://ComposableArchitecture/documentation/ComposableArchitecture/MigratingTo1.5":{"identifier":"doc:\/\/ComposableArchitecture\/documentation\/ComposableArchitecture\/MigratingTo1.5","url":"\/documentation\/composablearchitecture\/migratingto1.5","title":"Migrating to 1.5","role":"article","abstract":[{"text":"Update your code to make use of the new ","type":"text"},{"isActive":true,"type":"reference","identifier":"doc:\/\/ComposableArchitecture\/documentation\/ComposableArchitecture\/Store\/scope(state:action:)-90255"},{"text":" operation on ","type":"text"},{"isActive":true,"type":"reference","identifier":"doc:\/\/ComposableArchitecture\/documentation\/ComposableArchitecture\/Store"},{"text":" ","type":"text"},{"text":"in order to improve the performance of your features and simplify the usage of navigation APIs.","type":"text"}],"type":"topic","kind":"article"},"doc://ComposableArchitecture/documentation/ComposableArchitecture/Reducer/dependency(_:)":{"title":"dependency(_:)","fragments":[{"kind":"keyword","text":"func"},{"kind":"text","text":" "},{"kind":"identifier","text":"dependency"},{"kind":"text","text":"<"},{"kind":"genericParameter","text":"Value"},{"kind":"text","text":">("},{"kind":"typeIdentifier","text":"Value"},{"kind":"text","text":") -> "},{"kind":"typeIdentifier","text":"_DependencyKeyWritingReducer"},{"kind":"text","text":"<"},{"kind":"typeIdentifier","text":"Self"},{"kind":"text","text":">"}],"url":"\/documentation\/composablearchitecture\/reducer\/dependency(_:)","identifier":"doc:\/\/ComposableArchitecture\/documentation\/ComposableArchitecture\/Reducer\/dependency(_:)","type":"topic","abstract":[{"type":"text","text":"Places a value in the reducer’s dependencies."}],"role":"symbol","kind":"symbol"},"doc://ComposableArchitecture/documentation/ComposableArchitecture/Effect":{"role":"symbol","fragments":[{"text":"struct","kind":"keyword"},{"text":" ","kind":"text"},{"text":"Effect","kind":"identifier"}],"navigatorTitle":[{"text":"Effect","kind":"identifier"}],"kind":"symbol","type":"topic","abstract":[],"title":"Effect","identifier":"doc:\/\/ComposableArchitecture\/documentation\/ComposableArchitecture\/Effect","url":"\/documentation\/composablearchitecture\/effect"},"doc://ComposableArchitecture/documentation/ComposableArchitecture/MigratingTo1.4#Identified-actions":{"type":"topic","kind":"section","abstract":[],"identifier":"doc:\/\/ComposableArchitecture\/documentation\/ComposableArchitecture\/MigratingTo1.4#Identified-actions","url":"\/documentation\/composablearchitecture\/migratingto1.4#Identified-actions","title":"Identified actions"},"doc://ComposableArchitecture/documentation/ComposableArchitecture/MigratingTo1.14":{"title":"Migrating to 1.14","type":"topic","url":"\/documentation\/composablearchitecture\/migratingto1.14","role":"article","identifier":"doc:\/\/ComposableArchitecture\/documentation\/ComposableArchitecture\/MigratingTo1.14","abstract":[{"type":"text","text":"The "},{"isActive":true,"type":"reference","identifier":"doc:\/\/ComposableArchitecture\/documentation\/ComposableArchitecture\/Store"},{"type":"text","text":" type is now officially "},{"code":"@MainActor","type":"codeVoice"},{"type":"text","text":" isolated."}],"kind":"article"},"doc://ComposableArchitecture/documentation/ComposableArchitecture/Store":{"title":"Store","identifier":"doc:\/\/ComposableArchitecture\/documentation\/ComposableArchitecture\/Store","type":"topic","kind":"symbol","url":"\/documentation\/composablearchitecture\/store","abstract":[{"type":"text","text":"A store represents the runtime that powers the application. It is the object that you will pass"},{"type":"text","text":" "},{"type":"text","text":"around to views that need to interact with the application."}],"fragments":[{"text":"class","kind":"keyword"},{"text":" ","kind":"text"},{"text":"Store","kind":"identifier"}],"navigatorTitle":[{"text":"Store","kind":"identifier"}],"role":"symbol"},"doc://ComposableArchitecture/documentation/ComposableArchitecture/MigratingTo1.11":{"type":"topic","kind":"article","identifier":"doc:\/\/ComposableArchitecture\/documentation\/ComposableArchitecture\/MigratingTo1.11","abstract":[{"text":"Update your code to use the new ","type":"text"},{"code":"withLock","type":"codeVoice"},{"text":" method for mutating shared state from asynchronous","type":"text"},{"text":" ","type":"text"},{"text":"contexts, rather than mutating the underlying wrapped value directly.","type":"text"}],"url":"\/documentation\/composablearchitecture\/migratingto1.11","role":"article","title":"Migrating to 1.11"},"doc://ComposableArchitecture/documentation/ComposableArchitecture/MigratingTo1.9":{"type":"topic","abstract":[{"text":"Update your code to make use of the new ","type":"text"},{"type":"codeVoice","code":"TestStore\/send(_:assert:fileID:file:line:column:)-8877x"},{"text":"","type":"text"},{"text":" ","type":"text"},{"text":"method on ","type":"text"},{"identifier":"doc:\/\/ComposableArchitecture\/documentation\/ComposableArchitecture\/TestStore","isActive":true,"type":"reference"},{"text":" which gives a succinct syntax for sending actions with case key paths, and","type":"text"},{"text":" ","type":"text"},{"text":"the ","type":"text"},{"identifier":"doc:\/\/ComposableArchitecture\/documentation\/ComposableArchitecture\/Reducer\/dependency(_:)","isActive":true,"type":"reference"},{"text":" method for overriding dependencies.","type":"text"}],"kind":"article","role":"article","title":"Migrating to 1.9","identifier":"doc:\/\/ComposableArchitecture\/documentation\/ComposableArchitecture\/MigratingTo1.9","url":"\/documentation\/composablearchitecture\/migratingto1.9"},"#Using-the-Reducer-macro":{"type":"link","titleInlineContent":[{"type":"text","text":"Using the @Reducer macro"}],"identifier":"#Using-the-Reducer-macro","url":"#Using-the-Reducer-macro","title":"Using the @Reducer macro"},"doc://ComposableArchitecture/documentation/ComposableArchitecture/Reducer/forEach(_:action:element:fileID:filePath:line:column:)-6zye8":{"title":"forEach(_:action:element:fileID:filePath:line:column:)","abstract":[{"text":"Embeds a child reducer in a parent domain that works on elements of a collection in parent","type":"text"},{"text":" ","type":"text"},{"text":"state.","type":"text"}],"fragments":[{"text":"func","kind":"keyword"},{"text":" ","kind":"text"},{"text":"forEach","kind":"identifier"},{"text":"<","kind":"text"},{"text":"ElementState","kind":"genericParameter"},{"text":", ","kind":"text"},{"text":"ElementAction","kind":"genericParameter"},{"text":", ","kind":"text"},{"text":"ID","kind":"genericParameter"},{"text":", ","kind":"text"},{"text":"Element","kind":"genericParameter"},{"text":">(","kind":"text"},{"text":"WritableKeyPath","preciseIdentifier":"s:s15WritableKeyPathC","kind":"typeIdentifier"},{"text":"<","kind":"text"},{"text":"Self","kind":"typeIdentifier"},{"text":".","kind":"text"},{"text":"State","preciseIdentifier":"s:22ComposableArchitecture7ReducerP5StateQa","kind":"typeIdentifier"},{"text":", ","kind":"text"},{"text":"IdentifiedArray","preciseIdentifier":"s:21IdentifiedCollections0A5ArrayV","kind":"typeIdentifier"},{"text":"<","kind":"text"},{"text":"ID","kind":"typeIdentifier"},{"text":", ","kind":"text"},{"text":"ElementState","kind":"typeIdentifier"},{"text":">>, ","kind":"text"},{"text":"action","kind":"externalParam"},{"text":": ","kind":"text"},{"text":"CaseKeyPath","preciseIdentifier":"s:9CasePaths0A7KeyPatha","kind":"typeIdentifier"},{"text":"<","kind":"text"},{"text":"Self","kind":"typeIdentifier"},{"text":".","kind":"text"},{"text":"Action","preciseIdentifier":"s:22ComposableArchitecture7ReducerP6ActionQa","kind":"typeIdentifier"},{"text":", ","kind":"text"},{"text":"IdentifiedAction","preciseIdentifier":"s:22ComposableArchitecture16IdentifiedActionO","kind":"typeIdentifier"},{"text":"<","kind":"text"},{"text":"ID","kind":"typeIdentifier"},{"text":", ","kind":"text"},{"text":"ElementAction","kind":"typeIdentifier"},{"text":">>, ","kind":"text"},{"text":"element","kind":"externalParam"},{"text":": () -> ","kind":"text"},{"text":"Element","kind":"typeIdentifier"},{"text":", ","kind":"text"},{"text":"fileID","kind":"externalParam"},{"text":": ","kind":"text"},{"text":"StaticString","preciseIdentifier":"s:s12StaticStringV","kind":"typeIdentifier"},{"text":", ","kind":"text"},{"text":"filePath","kind":"externalParam"},{"text":": ","kind":"text"},{"text":"StaticString","preciseIdentifier":"s:s12StaticStringV","kind":"typeIdentifier"},{"text":", ","kind":"text"},{"text":"line","kind":"externalParam"},{"text":": ","kind":"text"},{"text":"UInt","preciseIdentifier":"s:Su","kind":"typeIdentifier"},{"text":", ","kind":"text"},{"text":"column","kind":"externalParam"},{"text":": ","kind":"text"},{"text":"UInt","preciseIdentifier":"s:Su","kind":"typeIdentifier"},{"text":") -> ","kind":"text"},{"text":"some","kind":"keyword"},{"text":" ","kind":"text"},{"text":"Reducer","preciseIdentifier":"s:22ComposableArchitecture7ReducerP","kind":"typeIdentifier"},{"text":"<","kind":"text"},{"text":"Self","kind":"typeIdentifier"},{"text":".","kind":"text"},{"text":"State","preciseIdentifier":"s:22ComposableArchitecture7ReducerP5StateQa","kind":"typeIdentifier"},{"text":", ","kind":"text"},{"text":"Self","kind":"typeIdentifier"},{"text":".","kind":"text"},{"text":"Action","preciseIdentifier":"s:22ComposableArchitecture7ReducerP6ActionQa","kind":"typeIdentifier"},{"text":">\n","kind":"text"}],"identifier":"doc:\/\/ComposableArchitecture\/documentation\/ComposableArchitecture\/Reducer\/forEach(_:action:element:fileID:filePath:line:column:)-6zye8","kind":"symbol","role":"symbol","type":"topic","url":"\/documentation\/composablearchitecture\/reducer\/foreach(_:action:element:fileid:filepath:line:column:)-6zye8"},"http://github.com/pointfreeco/swift-composable-architecture/discussions":{"type":"link","titleInlineContent":[{"type":"text","text":"discussion"}],"identifier":"http:\/\/github.com\/pointfreeco\/swift-composable-architecture\/discussions","url":"http:\/\/github.com\/pointfreeco\/swift-composable-architecture\/discussions","title":"discussion"},"doc://ComposableArchitecture/documentation/ComposableArchitecture/MigratingTo1.17.1":{"url":"\/documentation\/composablearchitecture\/migratingto1.17.1","abstract":[{"text":"The Sharing library has graduated, with backwards-incompatible changes, to 2.0, and the Composable","type":"text"},{"text":" ","type":"text"},{"text":"Architecture has been updated to extend support to this new version.","type":"text"}],"kind":"article","role":"article","title":"Migrating to 1.17.1","identifier":"doc:\/\/ComposableArchitecture\/documentation\/ComposableArchitecture\/MigratingTo1.17.1","type":"topic"},"doc://ComposableArchitecture/documentation/ComposableArchitecture/Reducer":{"role":"symbol","fragments":[{"kind":"keyword","text":"protocol"},{"kind":"text","text":" "},{"kind":"identifier","text":"Reducer"}],"kind":"symbol","abstract":[{"type":"text","text":"A protocol that describes how to evolve the current state of an application to the next state,"},{"type":"text","text":" "},{"type":"text","text":"given an action, and describes what "},{"type":"reference","identifier":"doc:\/\/ComposableArchitecture\/documentation\/ComposableArchitecture\/Effect","isActive":true},{"type":"text","text":"s should be executed later by the store, if any."}],"type":"topic","url":"\/documentation\/composablearchitecture\/reducer","title":"Reducer","identifier":"doc:\/\/ComposableArchitecture\/documentation\/ComposableArchitecture\/Reducer","navigatorTitle":[{"kind":"identifier","text":"Reducer"}]},"doc://ComposableArchitecture/documentation/ComposableArchitecture/PresentationAction/presented(_:)":{"kind":"symbol","url":"\/documentation\/composablearchitecture\/presentationaction\/presented(_:)","role":"symbol","identifier":"doc:\/\/ComposableArchitecture\/documentation\/ComposableArchitecture\/PresentationAction\/presented(_:)","title":"PresentationAction.presented(_:)","fragments":[{"text":"case","kind":"keyword"},{"text":" ","kind":"text"},{"text":"presented","kind":"identifier"},{"text":"(","kind":"text"},{"text":"Action","kind":"typeIdentifier"},{"text":")","kind":"text"}],"abstract":[{"text":"An action sent to the associated, non-","type":"text"},{"code":"nil","type":"codeVoice"},{"text":" presentation state.","type":"text"}],"type":"topic"},"doc://ComposableArchitecture/documentation/ComposableArchitecture/Reducer()":{"type":"topic","role":"symbol","identifier":"doc:\/\/ComposableArchitecture\/documentation\/ComposableArchitecture\/Reducer()","fragments":[{"kind":"keyword","text":"macro"},{"kind":"text","text":" "},{"kind":"identifier","text":"Reducer"},{"kind":"text","text":"()"}],"title":"Reducer()","kind":"symbol","abstract":[{"type":"text","text":"Helps implement the conformance to the "},{"type":"reference","isActive":true,"identifier":"doc:\/\/ComposableArchitecture\/documentation\/ComposableArchitecture\/Reducer"},{"type":"text","text":" protocol for a type."}],"url":"\/documentation\/composablearchitecture\/reducer()"},"doc://ComposableArchitecture/documentation/ComposableArchitecture/ForEachStore":{"title":"ForEachStore","deprecated":true,"identifier":"doc:\/\/ComposableArchitecture\/documentation\/ComposableArchitecture\/ForEachStore","kind":"symbol","url":"\/documentation\/composablearchitecture\/foreachstore","role":"symbol","fragments":[{"kind":"keyword","text":"struct"},{"kind":"text","text":" "},{"kind":"identifier","text":"ForEachStore"}],"navigatorTitle":[{"kind":"identifier","text":"ForEachStore"}],"type":"topic","abstract":[{"text":"A Composable Architecture-friendly wrapper around ","type":"text"},{"type":"codeVoice","code":"ForEach"},{"text":" that simplifies working with","type":"text"},{"text":" ","type":"text"},{"text":"collections of state.","type":"text"}]},"doc://ComposableArchitecture/documentation/ComposableArchitecture":{"abstract":[{"type":"text","text":"The Composable Architecture (TCA, for short) is a library for building applications in a consistent"},{"type":"text","text":" "},{"type":"text","text":"and understandable way, with composition, testing, and ergonomics in mind. It can be used in"},{"type":"text","text":" "},{"type":"text","text":"SwiftUI, UIKit, and more, and on any Apple platform (iOS, macOS, tvOS, and watchOS)."}],"type":"topic","identifier":"doc:\/\/ComposableArchitecture\/documentation\/ComposableArchitecture","title":"ComposableArchitecture","role":"collection","url":"\/documentation\/composablearchitecture","kind":"symbol"},"doc://ComposableArchitecture/documentation/ComposableArchitecture/TestStore":{"kind":"symbol","title":"TestStore","navigatorTitle":[{"text":"TestStore","kind":"identifier"}],"abstract":[{"type":"text","text":"A testable runtime for a reducer."}],"identifier":"doc:\/\/ComposableArchitecture\/documentation\/ComposableArchitecture\/TestStore","fragments":[{"text":"class","kind":"keyword"},{"text":" ","kind":"text"},{"text":"TestStore","kind":"identifier"}],"role":"symbol","type":"topic","url":"\/documentation\/composablearchitecture\/teststore"},"#Identified-actions":{"type":"link","titleInlineContent":[{"type":"text","text":"Identified actions"}],"identifier":"#Identified-actions","url":"#Identified-actions","title":"Identified actions"},"#Using-case-key-paths":{"type":"link","titleInlineContent":[{"type":"text","text":"Using case key paths"}],"identifier":"#Using-case-key-paths","url":"#Using-case-key-paths","title":"Using case key paths"}}}