{"abstract":[{"type":"text","text":"Provides a view with access to a feature’s "},{"identifier":"doc:\/\/ComposableArchitecture\/documentation\/ComposableArchitecture\/ViewAction","isActive":true,"type":"reference"},{"type":"text","text":"s."}],"hierarchy":{"paths":[["doc:\/\/ComposableArchitecture\/documentation\/ComposableArchitecture","doc:\/\/ComposableArchitecture\/documentation\/ComposableArchitecture\/Reducer","doc:\/\/ComposableArchitecture\/documentation\/ComposableArchitecture\/Reducer\/Action"]]},"identifier":{"url":"doc:\/\/ComposableArchitecture\/documentation\/ComposableArchitecture\/ViewAction(for:)","interfaceLanguage":"swift"},"variants":[{"paths":["\/documentation\/composablearchitecture\/viewaction(for:)"],"traits":[{"interfaceLanguage":"swift"}]}],"schemaVersion":{"major":0,"minor":3,"patch":0},"seeAlsoSections":[{"generated":true,"anchor":"View-actions","identifiers":["doc:\/\/ComposableArchitecture\/documentation\/ComposableArchitecture\/ViewAction","doc:\/\/ComposableArchitecture\/documentation\/ComposableArchitecture\/ViewActionSending"],"title":"View actions"}],"primaryContentSections":[{"kind":"declarations","declarations":[{"platforms":["macOS"],"languages":["swift"],"tokens":[{"text":"@attached","kind":"attribute"},{"text":"(extension, conformances: ","kind":"text"},{"preciseIdentifier":"s:22ComposableArchitecture17ViewActionSendingP","text":"ViewActionSending","identifier":"doc:\/\/ComposableArchitecture\/documentation\/ComposableArchitecture\/ViewActionSending","kind":"typeIdentifier"},{"text":") ","kind":"text"},{"text":"macro","kind":"keyword"},{"text":" ","kind":"text"},{"kind":"identifier","text":"ViewAction"},{"text":"<","kind":"text"},{"text":"R","kind":"genericParameter"},{"text":">(","kind":"text"},{"text":"for","kind":"externalParam"},{"kind":"text","text":": "},{"kind":"typeIdentifier","text":"R"},{"kind":"text","text":".Type) "},{"text":"where","kind":"keyword"},{"kind":"text","text":" "},{"text":"R","kind":"typeIdentifier"},{"text":" : ","kind":"text"},{"preciseIdentifier":"s:22ComposableArchitecture7ReducerP","identifier":"doc:\/\/ComposableArchitecture\/documentation\/ComposableArchitecture\/Reducer","text":"Reducer","kind":"typeIdentifier"},{"kind":"text","text":", "},{"kind":"typeIdentifier","text":"R"},{"text":".","kind":"text"},{"kind":"typeIdentifier","identifier":"doc:\/\/ComposableArchitecture\/documentation\/ComposableArchitecture\/Reducer\/Action","preciseIdentifier":"s:22ComposableArchitecture7ReducerP6ActionQa","text":"Action"},{"text":" : ","kind":"text"},{"text":"ViewAction","identifier":"doc:\/\/ComposableArchitecture\/documentation\/ComposableArchitecture\/ViewAction","preciseIdentifier":"s:22ComposableArchitecture10ViewActionP","kind":"typeIdentifier"}]}]},{"kind":"content","content":[{"level":2,"anchor":"overview","type":"heading","text":"Overview"},{"inlineContent":[{"type":"text","text":"If you want to restrict what actions can be sent from the view you can use this macro along with the"},{"text":" ","type":"text"},{"identifier":"doc:\/\/ComposableArchitecture\/documentation\/ComposableArchitecture\/ViewAction","type":"reference","isActive":true},{"type":"text","text":" protocol. You start by conforming your reducer’s "},{"type":"codeVoice","code":"Action"},{"type":"text","text":" enum to the"},{"type":"text","text":" "},{"identifier":"doc:\/\/ComposableArchitecture\/documentation\/ComposableArchitecture\/ViewAction","type":"reference","isActive":true},{"text":" protocol, and moving view-specific actions to its own inner enum:","type":"text"}],"type":"paragraph"},{"type":"codeListing","syntax":"swift","code":["@Reducer","struct Feature {","  struct State { \/* ... *\/ }","  enum Action: ViewAction {","    case loginResponse(Bool)","    case view(View)","","    enum View {","      case loginButtonTapped","    }","  }","  \/\/ ...","}"]},{"inlineContent":[{"text":"Then you can apply the ","type":"text"},{"identifier":"doc:\/\/ComposableArchitecture\/documentation\/ComposableArchitecture\/ViewAction(for:)","type":"reference","isActive":true},{"text":" macro to your view by specifying the type of the","type":"text"},{"type":"text","text":" "},{"type":"text","text":"reducer that powers the view:"}],"type":"paragraph"},{"code":["@ViewAction(for: Feature.self)","struct FeatureView: View {","  let store: StoreOf<Feature>","  \/\/ ...","}"],"type":"codeListing","syntax":"swift"},{"inlineContent":[{"type":"text","text":"The macro does two things:"}],"type":"paragraph"},{"items":[{"content":[{"type":"paragraph","inlineContent":[{"type":"text","text":"It adds a "},{"code":"send","type":"codeVoice"},{"type":"text","text":" method to the view that you can use instead of "},{"code":"store.send","type":"codeVoice"},{"type":"text","text":". This allows you"},{"text":" ","type":"text"},{"text":"to send view actions more simply, without wrapping the action in ","type":"text"},{"code":".view(…)","type":"codeVoice"},{"type":"text","text":":"}]},{"syntax":"diff","type":"codeListing","code":[" Button(\"Login\") {","-  store.send(.view(.loginButtonTapped))","+  send(.loginButtonTapped)"," }"]}]},{"content":[{"type":"paragraph","inlineContent":[{"type":"text","text":"It creates warning diagnostics if you try sending actions through "},{"type":"codeVoice","code":"store.send"},{"text":" rather than","type":"text"},{"type":"text","text":" "},{"type":"text","text":"using the "},{"code":"send","type":"codeVoice"},{"type":"text","text":" method on the view:"}]},{"syntax":"swift","type":"codeListing","code":["Button(\"Login\") {","  store.send(.view(.loginButtonTapped))","\/\/┬─────────","\/\/╰─ ⚠️ Do not use 'store.send' directly when using '@ViewAction'","}"]}]}],"type":"unorderedList"}]}],"kind":"symbol","sections":[],"metadata":{"modules":[{"name":"ComposableArchitecture"}],"fragments":[{"kind":"keyword","text":"macro"},{"kind":"text","text":" "},{"text":"ViewAction","kind":"identifier"},{"kind":"text","text":"<"},{"text":"R","kind":"genericParameter"},{"kind":"text","text":">("},{"text":"for","kind":"externalParam"},{"kind":"text","text":": "},{"kind":"typeIdentifier","text":"R"},{"text":".Type)","kind":"text"}],"roleHeading":"Macro","role":"symbol","symbolKind":"macro","title":"ViewAction(for:)","externalID":"s:22ComposableArchitecture10ViewAction3foryxm_tcAA7ReducerRzAaB0D0Rpzlufm"},"references":{"doc://ComposableArchitecture/documentation/ComposableArchitecture/Reducer/Action":{"required":true,"url":"\/documentation\/composablearchitecture\/reducer\/action","identifier":"doc:\/\/ComposableArchitecture\/documentation\/ComposableArchitecture\/Reducer\/Action","title":"Action","abstract":[{"text":"A type that holds all possible actions that cause the ","type":"text"},{"type":"reference","identifier":"doc:\/\/ComposableArchitecture\/documentation\/ComposableArchitecture\/Reducer\/State","isActive":true},{"type":"text","text":" of the reducer to change"},{"type":"text","text":" "},{"text":"and\/or kick off a side ","type":"text"},{"identifier":"doc:\/\/ComposableArchitecture\/documentation\/ComposableArchitecture\/Effect","isActive":true,"type":"reference"},{"type":"text","text":" that can communicate with the outside world."}],"fragments":[{"text":"associatedtype","kind":"keyword"},{"text":" ","kind":"text"},{"kind":"identifier","text":"Action"}],"kind":"symbol","type":"topic","role":"symbol"},"doc://ComposableArchitecture/documentation/ComposableArchitecture":{"type":"topic","abstract":[{"type":"text","text":"The Composable Architecture (TCA, for short) is a library for building applications in a consistent"},{"text":" ","type":"text"},{"text":"and understandable way, with composition, testing, and ergonomics in mind. It can be used in","type":"text"},{"text":" ","type":"text"},{"text":"SwiftUI, UIKit, and more, and on any Apple platform (iOS, macOS, tvOS, and watchOS).","type":"text"}],"url":"\/documentation\/composablearchitecture","identifier":"doc:\/\/ComposableArchitecture\/documentation\/ComposableArchitecture","kind":"symbol","title":"ComposableArchitecture","role":"collection"},"doc://ComposableArchitecture/documentation/ComposableArchitecture/Store":{"role":"symbol","kind":"symbol","type":"topic","fragments":[{"kind":"keyword","text":"class"},{"kind":"text","text":" "},{"text":"Store","kind":"identifier"}],"navigatorTitle":[{"kind":"identifier","text":"Store"}],"identifier":"doc:\/\/ComposableArchitecture\/documentation\/ComposableArchitecture\/Store","title":"Store","url":"\/documentation\/composablearchitecture\/store","abstract":[{"text":"A store represents the runtime that powers the application. It is the object that you will pass","type":"text"},{"type":"text","text":" "},{"type":"text","text":"around to views that need to interact with the application."}]},"doc://ComposableArchitecture/documentation/ComposableArchitecture/ViewAction(for:)":{"title":"ViewAction(for:)","url":"\/documentation\/composablearchitecture\/viewaction(for:)","type":"topic","kind":"symbol","abstract":[{"text":"Provides a view with access to a feature’s ","type":"text"},{"identifier":"doc:\/\/ComposableArchitecture\/documentation\/ComposableArchitecture\/ViewAction","isActive":true,"type":"reference"},{"text":"s.","type":"text"}],"identifier":"doc:\/\/ComposableArchitecture\/documentation\/ComposableArchitecture\/ViewAction(for:)","role":"symbol","fragments":[{"text":"macro","kind":"keyword"},{"text":" ","kind":"text"},{"text":"ViewAction","kind":"identifier"},{"kind":"text","text":"<"},{"kind":"genericParameter","text":"R"},{"text":">(","kind":"text"},{"kind":"externalParam","text":"for"},{"kind":"text","text":": "},{"text":"R","kind":"typeIdentifier"},{"text":".Type)","kind":"text"}]},"doc://ComposableArchitecture/documentation/ComposableArchitecture/ViewActionSending":{"identifier":"doc:\/\/ComposableArchitecture\/documentation\/ComposableArchitecture\/ViewActionSending","url":"\/documentation\/composablearchitecture\/viewactionsending","type":"topic","fragments":[{"kind":"keyword","text":"protocol"},{"kind":"text","text":" "},{"text":"ViewActionSending","kind":"identifier"}],"kind":"symbol","role":"symbol","abstract":[{"type":"text","text":"A type that represents a view with a "},{"isActive":true,"type":"reference","identifier":"doc:\/\/ComposableArchitecture\/documentation\/ComposableArchitecture\/Store"},{"type":"text","text":" that can send "},{"identifier":"doc:\/\/ComposableArchitecture\/documentation\/ComposableArchitecture\/ViewAction","type":"reference","isActive":true},{"text":"s.","type":"text"}],"title":"ViewActionSending","navigatorTitle":[{"text":"ViewActionSending","kind":"identifier"}]},"doc://ComposableArchitecture/documentation/ComposableArchitecture/Effect":{"kind":"symbol","abstract":[],"title":"Effect","role":"symbol","navigatorTitle":[{"kind":"identifier","text":"Effect"}],"identifier":"doc:\/\/ComposableArchitecture\/documentation\/ComposableArchitecture\/Effect","type":"topic","url":"\/documentation\/composablearchitecture\/effect","fragments":[{"text":"struct","kind":"keyword"},{"text":" ","kind":"text"},{"kind":"identifier","text":"Effect"}]},"doc://ComposableArchitecture/documentation/ComposableArchitecture/ViewAction":{"title":"ViewAction","url":"\/documentation\/composablearchitecture\/viewaction","type":"topic","kind":"symbol","abstract":[{"type":"text","text":"Defines the actions that can be sent from a view."}],"identifier":"doc:\/\/ComposableArchitecture\/documentation\/ComposableArchitecture\/ViewAction","role":"symbol","navigatorTitle":[{"text":"ViewAction","kind":"identifier"}],"fragments":[{"text":"protocol","kind":"keyword"},{"kind":"text","text":" "},{"kind":"identifier","text":"ViewAction"}]},"doc://ComposableArchitecture/documentation/ComposableArchitecture/Reducer/State":{"abstract":[{"text":"A type that holds the current state of the reducer.","type":"text"}],"url":"\/documentation\/composablearchitecture\/reducer\/state","fragments":[{"kind":"keyword","text":"associatedtype"},{"kind":"text","text":" "},{"text":"State","kind":"identifier"}],"identifier":"doc:\/\/ComposableArchitecture\/documentation\/ComposableArchitecture\/Reducer\/State","required":true,"type":"topic","title":"State","kind":"symbol","role":"symbol"},"doc://ComposableArchitecture/documentation/ComposableArchitecture/Reducer":{"kind":"symbol","abstract":[{"text":"A protocol that describes how to evolve the current state of an application to the next state,","type":"text"},{"type":"text","text":" "},{"text":"given an action, and describes what ","type":"text"},{"type":"reference","identifier":"doc:\/\/ComposableArchitecture\/documentation\/ComposableArchitecture\/Effect","isActive":true},{"type":"text","text":"s should be executed later by the store, if any."}],"title":"Reducer","role":"symbol","navigatorTitle":[{"text":"Reducer","kind":"identifier"}],"identifier":"doc:\/\/ComposableArchitecture\/documentation\/ComposableArchitecture\/Reducer","type":"topic","url":"\/documentation\/composablearchitecture\/reducer","fragments":[{"kind":"keyword","text":"protocol"},{"kind":"text","text":" "},{"text":"Reducer","kind":"identifier"}]}}}